doubaotrans/__init__.py
doubaotrans/doubaotrans/__init__.py
doubaotrans/doubaotrans/py.typed
doubaotrans-1.2.2.1.dist-info/LICENSE
doubaotrans-1.2.2.1.dist-info/METADATA
doubaotrans-1.2.2.1.dist-info/WHEEL
doubaotrans-1.2.2.1.dist-info/top_level.txt
doubaotrans-1.2.2.1.dist-info/RECORD
